{
    "$schema": "../utils/material_schema.json",
    "name": "Phong",
    "pipeline": {
        "vs": "assets/shaders/phong.hlsl",
        "ps": "assets/shaders/phong.hlsl",
        "primitive": "TriangleList",
        "depth_test": true
    },
    "parameters": [
        {
            "name": "shininess",
            "type": "float",
            "default": 1.0
        },
        {
            "name": "diffuse",
            "type": "color",
            "default": [
                1.0,
                1.0,
                1.0,
                1.0
            ]
        },
        {
            "name": "specular",
            "type": "color",
            "default": [
                1.0,
                1.0,
                1.0,
                1.0
            ]
        },
        {
            "name": "ambient",
            "type": "color",
            "default": [
                1.0,
                1.0,
                1.0,
                1.0
            ]
        },
        {
            "name": "emissive",
            "type": "color",
            "default": [
                1.0,
                1.0,
                1.0,
                1.0
            ]
        }
    ]
}